dbtlogs/__init__.py
dbtlogs/main.py
dbtlogs_prebuilt-0.6.dist-info/METADATA
dbtlogs_prebuilt-0.6.dist-info/WHEEL
dbtlogs_prebuilt-0.6.dist-info/entry_points.txt
dbtlogs_prebuilt-0.6.dist-info/top_level.txt
dbtlogs_prebuilt-0.6.dist-info/RECORD
