Metadata-Version: 2.1
Name: dbtlogs-prebuilt
Version: 0.6
Requires-Dist: click
Requires-Dist: databricks-sql-connector
Requires-Dist: requests
Requires-Dist: pytz
Requires-Dist: typing
Requires-Dist: datetime
Requires-Dist: apache-airflow
